meetstream/__init__.py
meetstream/api.py
meetstream-0.1.0.dist-info/licenses/LICENSE
meetstream-0.1.0.dist-info/METADATA
meetstream-0.1.0.dist-info/WHEEL
meetstream-0.1.0.dist-info/top_level.txt
meetstream-0.1.0.dist-info/RECORD
