Metadata-Version: 2.4
Name: meetstream
Version: 0.1.0
Summary: Unofficial Python Client for Meetstream.ai API
Author-email: GalacticApricot <me@galacticapricot.dev>
License: MIT
Project-URL: Homepage, https://github.com/GalacticApricot/MeetStream.py
Project-URL: Documentation, https://github.com/GalacticApricot/MeetStream.py/blob/main/README.md
Project-URL: Issues, https://github.com/GalacticApricot/MeetStream.py/issues
Requires-Python: >=3.8
License-File: LICENSE
Requires-Dist: requests>=2.20.0
Dynamic: license-file
